autointent/__init__.py
autointent/_embedder.py
autointent/_utils.py
autointent/configs/__init__.py
autointent/configs/_inference_cli.py
autointent/configs/_inference_pipeline.py
autointent/configs/_name.py
autointent/configs/_node.py
autointent/configs/_optimization_cli.py
autointent/configs/_pipeline_optimizer.py
autointent/context/__init__.py
autointent/context/_context.py
autointent/context/_utils.py
autointent/context/data_handler/__init__.py
autointent/context/data_handler/_data_handler.py
autointent/context/data_handler/_dataset.py
autointent/context/data_handler/_reader.py
autointent/context/data_handler/_schemas.py
autointent/context/data_handler/_stratification.py
autointent/context/data_handler/_validation.py
autointent/context/optimization_info/__init__.py
autointent/context/optimization_info/_data_models.py
autointent/context/optimization_info/_logger.py
autointent/context/optimization_info/_optimization_info.py
autointent/context/vector_index_client/__init__.py
autointent/context/vector_index_client/_cache.py
autointent/context/vector_index_client/_vector_index.py
autointent/context/vector_index_client/_vector_index_client.py
autointent/custom_types.py
autointent/datafiles/__init__.py
autointent/datafiles/banking77.json
autointent/datafiles/default-multiclass-config.yaml
autointent/datafiles/default-multilabel-config.yaml
autointent/datafiles/dstc3-20shot.json
autointent/datafiles/inference-config-example.yaml
autointent/generation/__init__.py
autointent/generation/description_generation.py
autointent/generation/prompt_scheme.py
autointent/generation/prompts.py
autointent/metrics/__init__.py
autointent/metrics/_converter.py
autointent/metrics/_custom_types.py
autointent/metrics/prediction.py
autointent/metrics/regexp.py
autointent/metrics/retrieval.py
autointent/metrics/scoring.py
autointent/modules/__init__.py
autointent/modules/_base.py
autointent/modules/_regexp.py
autointent/modules/prediction/__init__.py
autointent/modules/prediction/_adaptive.py
test_ci_release-0.2.12.dist-info/METADATA
test_ci_release-0.2.12.dist-info/WHEEL
test_ci_release-0.2.12.dist-info/entry_points.txt
test_ci_release-0.2.12.dist-info/RECORD
