Metadata-Version: 2.1
Name: test-ci-release
Version: 0.2.12
Summary: A tool for automatically configuring a text classification pipeline for intent prediction.
Home-page: https://deeppavlov.github.io/AutoIntent/
Author: voorhs
Author-email: ilya_alekseev_2016@list.ru
Requires-Python: >=3.10,<4.0
Classifier: Programming Language :: Python :: 3
Classifier: Programming Language :: Python :: 3.10
Classifier: Programming Language :: Python :: 3.11
Classifier: Programming Language :: Python :: 3.12
Classifier: Programming Language :: Python :: 3.13
Requires-Dist: appdirs (>=1.4.4,<2.0.0)
Requires-Dist: datasets (>=3.1.0,<4.0.0)
Requires-Dist: faiss-cpu (>=1.9.0,<2.0.0)
Requires-Dist: hydra-core (>=1.3.2,<2.0.0)
Requires-Dist: openai (>=1.52.1,<2.0.0)
Requires-Dist: optuna (>=4.0.0,<5.0.0)
Requires-Dist: pathlib (>=1.0.1,<2.0.0)
Requires-Dist: pydantic (>=2.9.2,<3.0.0)
Requires-Dist: ruff (>=0.8.0,<0.9.0)
Requires-Dist: scikit-learn (==1.5.1)
Requires-Dist: scikit-multilearn (==0.2.0)
Requires-Dist: sentence-transformers (==3.0.1)
Requires-Dist: sre-yield (>=1.2,<2.0)
Requires-Dist: xeger (>=0.4.0,<0.5.0)
Project-URL: Documentation, https://deeppavlov.github.io/AutoIntent/
Project-URL: Repository, https://github.com/deeppavlov/AutoIntent
